tree_sitter_smali/__init__.pyi
tree_sitter_smali/cli.py
tree_sitter_smali/py.typed
tree_sitter_smali/binding.c
tree_sitter_smali/__init__.py
tree_sitter_smali/_binding.abi3.so
tree_sitter_smali/queries/locals.scm
tree_sitter_smali/queries/indents.scm
tree_sitter_smali/queries/injections.scm
tree_sitter_smali/queries/folds.scm
tree_sitter_smali/queries/highlights.scm
ts_smali-1.0.0.dist-info/LICENSE
ts_smali-1.0.0.dist-info/WHEEL
ts_smali-1.0.0.dist-info/entry_points.txt
ts_smali-1.0.0.dist-info/top_level.txt
ts_smali-1.0.0.dist-info/METADATA
ts_smali-1.0.0.dist-info/RECORD
