Metadata-Version: 2.1
Name: ts-smali
Version: 1.0.0
Summary: Smali grammar for tree-sitter
License: MIT
Project-URL: Homepage, https://git.sr.ht/~yotam/tree-sitter-smali
Keywords: incremental,parsing,tree-sitter,smali
Classifier: Intended Audience :: Developers
Classifier: License :: OSI Approved :: MIT License
Classifier: Topic :: Software Development :: Compilers
Classifier: Topic :: Text Processing :: Linguistic
Classifier: Typing :: Typed
Requires-Python: >=3.8
License-File: LICENSE
Provides-Extra: core
Requires-Dist: tree-sitter ~=0.21 ; extra == 'core'
